alignment_tools/__init__.py
alignment_tools/core.py
alignment_tools/digest.py
alignment_tools-0.1.6.dist-info/licenses/LICENSE
alignment_tools-0.1.6.dist-info/METADATA
alignment_tools-0.1.6.dist-info/WHEEL
alignment_tools-0.1.6.dist-info/top_level.txt
alignment_tools-0.1.6.dist-info/RECORD
