Metadata-Version: 2.4
Name: alignment_tools
Version: 0.1.6
Summary: Tools for AlphaFold PDB processing, SASA, Clustal, and InterPro annotation
Author: Amirhossein Sakhteman,Matthew The
Author-email: amirhossein.sakhteman@tume.de,matthew.the@tum.de
Classifier: Programming Language :: Python :: 3
Classifier: License :: OSI Approved :: MIT License
Requires-Python: >=3.7
License-File: LICENSE
Requires-Dist: pandas
Requires-Dist: numpy
Requires-Dist: matplotlib
Requires-Dist: seaborn
Requires-Dist: scipy
Requires-Dist: biopython
Requires-Dist: freesasa
Dynamic: author
Dynamic: author-email
Dynamic: classifier
Dynamic: description
Dynamic: description-content-type
Dynamic: license-file
Dynamic: requires-dist
Dynamic: requires-python
Dynamic: summary
